{
  "id": "8875450c-eeea-4796-b500-14b640064325",
  "prevId": "063353a9-734c-4b93-bfd7-393925dc6f01",
  "version": "7",
  "dialect": "postgresql",
  "tables": {
    "public.categories": {
      "name": "categories",
      "schema": "",
      "columns": {
        "id": {
          "name": "id",
          "type": "integer",
          "primaryKey": true,
          "notNull": true,
          "identity": {
            "type": "always",
            "name": "categories_id_seq",
            "schema": "public",
            "increment": "1",
            "startWith": "1",
            "minValue": "1",
            "maxValue": "2147483647",
            "cache": "1",
            "cycle": false
          }
        },
        "name": {
          "name": "name",
          "type": "varchar(255)",
          "primaryKey": false,
          "notNull": true
        }
      },
      "indexes": {},
      "foreignKeys": {},
      "compositePrimaryKeys": {},
      "uniqueConstraints": {},
      "policies": {},
      "checkConstraints": {},
      "isRLSEnabled": false
    },
    "public.post_categories": {
      "name": "post_categories",
      "schema": "",
      "columns": {
        "post_id": {
          "name": "post_id",
          "type": "integer",
          "primaryKey": false,
          "notNull": true
        },
        "category_id": {
          "name": "category_id",
          "type": "integer",
          "primaryKey": false,
          "notNull": true
        }
      },
      "indexes": {},
      "foreignKeys": {
        "post_categories_post_id_posts_id_fk": {
          "name": "post_categories_post_id_posts_id_fk",
          "tableFrom": "post_categories",
          "tableTo": "posts",
          "columnsFrom": [
            "post_id"
          ],
          "columnsTo": [
            "id"
          ],
          "onDelete": "no action",
          "onUpdate": "no action"
        },
        "post_categories_category_id_categories_id_fk": {
          "name": "post_categories_category_id_categories_id_fk",
          "tableFrom": "post_categories",
          "tableTo": "categories",
          "columnsFrom": [
            "category_id"
          ],
          "columnsTo": [
            "id"
          ],
          "onDelete": "no action",
          "onUpdate": "no action"
        }
      },
      "compositePrimaryKeys": {
        "post_categories_post_id_category_id_pk": {
          "name": "post_categories_post_id_category_id_pk",
          "columns": [
            "post_id",
            "category_id"
          ]
        }
      },
      "uniqueConstraints": {},
      "policies": {},
      "checkConstraints": {},
      "isRLSEnabled": false
    },
    "public.posts": {
      "name": "posts",
      "schema": "",
      "columns": {
        "id": {
          "name": "id",
          "type": "integer",
          "primaryKey": true,
          "notNull": true,
          "identity": {
            "type": "always",
            "name": "posts_id_seq",
            "schema": "public",
            "increment": "1",
            "startWith": "1",
            "minValue": "1",
            "maxValue": "2147483647",
            "cache": "1",
            "cycle": false
          }
        },
        "title": {
          "name": "title",
          "type": "varchar(255)",
          "primaryKey": false,
          "notNull": true
        },
        "average_rating": {
          "name": "average_rating",
          "type": "real",
          "primaryKey": false,
          "notNull": false,
          "default": 0
        },
        "user_id": {
          "name": "user_id",
          "type": "integer",
          "primaryKey": false,
          "notNull": false
        },
        "created_at": {
          "name": "created_at",
          "type": "timestamp",
          "primaryKey": false,
          "notNull": true,
          "default": "now()"
        },
        "updated_at": {
          "name": "updated_at",
          "type": "timestamp",
          "primaryKey": false,
          "notNull": true,
          "default": "now()"
        }
      },
      "indexes": {},
      "foreignKeys": {
        "posts_user_id_users_id_fk": {
          "name": "posts_user_id_users_id_fk",
          "tableFrom": "posts",
          "tableTo": "users",
          "columnsFrom": [
            "user_id"
          ],
          "columnsTo": [
            "id"
          ],
          "onDelete": "no action",
          "onUpdate": "no action"
        }
      },
      "compositePrimaryKeys": {},
      "uniqueConstraints": {},
      "policies": {},
      "checkConstraints": {},
      "isRLSEnabled": false
    },
    "public.user_preferences": {
      "name": "user_preferences",
      "schema": "",
      "columns": {
        "id": {
          "name": "id",
          "type": "integer",
          "primaryKey": true,
          "notNull": true,
          "identity": {
            "type": "always",
            "name": "user_preferences_id_seq",
            "schema": "public",
            "increment": "1",
            "startWith": "1",
            "minValue": "1",
            "maxValue": "2147483647",
            "cache": "1",
            "cycle": false
          }
        },
        "emailUpdates": {
          "name": "emailUpdates",
          "type": "boolean",
          "primaryKey": false,
          "notNull": true,
          "default": false
        },
        "user_id": {
          "name": "user_id",
          "type": "integer",
          "primaryKey": false,
          "notNull": false
        }
      },
      "indexes": {},
      "foreignKeys": {
        "user_preferences_user_id_users_id_fk": {
          "name": "user_preferences_user_id_users_id_fk",
          "tableFrom": "user_preferences",
          "tableTo": "users",
          "columnsFrom": [
            "user_id"
          ],
          "columnsTo": [
            "id"
          ],
          "onDelete": "no action",
          "onUpdate": "no action"
        }
      },
      "compositePrimaryKeys": {},
      "uniqueConstraints": {},
      "policies": {},
      "checkConstraints": {},
      "isRLSEnabled": false
    },
    "public.users": {
      "name": "users",
      "schema": "",
      "columns": {
        "id": {
          "name": "id",
          "type": "integer",
          "primaryKey": true,
          "notNull": true,
          "identity": {
            "type": "always",
            "name": "users_id_seq",
            "schema": "public",
            "increment": "1",
            "startWith": "1",
            "minValue": "1",
            "maxValue": "2147483647",
            "cache": "1",
            "cycle": false
          }
        },
        "name": {
          "name": "name",
          "type": "varchar(255)",
          "primaryKey": false,
          "notNull": true
        },
        "age": {
          "name": "age",
          "type": "integer",
          "primaryKey": false,
          "notNull": true
        },
        "email": {
          "name": "email",
          "type": "varchar(255)",
          "primaryKey": false,
          "notNull": true
        },
        "user_role": {
          "name": "user_role",
          "type": "user_role",
          "typeSchema": "public",
          "primaryKey": false,
          "notNull": true,
          "default": "'USER'"
        }
      },
      "indexes": {
        "email_index": {
          "name": "email_index",
          "columns": [
            {
              "expression": "email",
              "isExpression": false,
              "asc": true,
              "nulls": "last"
            }
          ],
          "isUnique": false,
          "concurrently": false,
          "method": "btree",
          "with": {}
        }
      },
      "foreignKeys": {},
      "compositePrimaryKeys": {},
      "uniqueConstraints": {
        "users_email_unique": {
          "name": "users_email_unique",
          "nullsNotDistinct": false,
          "columns": [
            "email"
          ]
        }
      },
      "policies": {},
      "checkConstraints": {},
      "isRLSEnabled": false
    }
  },
  "enums": {
    "public.user_role": {
      "name": "user_role",
      "schema": "public",
      "values": [
        "ADMIN",
        "USER"
      ]
    }
  },
  "schemas": {},
  "sequences": {},
  "roles": {},
  "policies": {},
  "views": {},
  "_meta": {
    "columns": {},
    "schemas": {},
    "tables": {}
  }
}